{
  "folderSpecificTemplates": [
    {
      "folderPath": "00-Inbox",
      "templateName": ""
    },
    {
      "folderPath": "00-Inbox/sessions",
      "templateName": ""
    },
    {
      "folderPath": "01-Projects",
      "templateName": ""
    },
    {
      "folderPath": "03-Daily",
      "templateName": ""
    }
  ],
  "disablePrompt": false,
  "debug": false,
  "templateTriggerOnFileCreation": true,
  "enableFolderTemplates": true,
  "folderTemplates": [
    {
      "folder": "00-Inbox",
      "template": "00-Inbox/_templates/T_Brainstorm.md"
    },
    {
      "folder": "00-Inbox/sessions",
      "template": "00-Inbox/_templates/T_Session_Notes.md"
    },
    {
      "folder": "03-Daily",
      "template": "00-Inbox/_templates/T_Session_Notes.md"
    }
  ]
}